{"TimeStamp": "1681483407", "SessionId": "1829456463078209559", "EventType": "INICIO"},
{"TimeStamp": "1681483415", "SessionId": "1829456463078209559", "EventType": "INICIOSALA", "RoomId": "1"},
{"TimeStamp": "1681483418", "SessionId": "1829456463078209559", "EventType": "BLOQUEOBALA", "Pos": "(51.17, -0.42)"},
{"TimeStamp": "1681483419", "SessionId": "1829456463078209559", "EventType": "BLOQUEOBALA", "Pos": "(52.89, -0.17)"},
{"TimeStamp": "1681483420", "SessionId": "1829456463078209559", "EventType": "BLOQUEOBALA", "Pos": "(54.47, 1.13)"},
{"TimeStamp": "1681483422", "SessionId": "1829456463078209559", "EventType": "MUERTEENEMIGO", "Pos": "(65.96, 3.90)", "EnemyID": "0"},
{"TimeStamp": "1681483426", "SessionId": "1829456463078209559", "EventType": "MUERTEJUGADOR", "Pos": "(64.28, 13.31)"},
{"TimeStamp": "1681483433", "SessionId": "1829456463078209559", "EventType": "FIN"},
